<?xml version="1.0" encoding="utf-8"?>
<tagset>
   <image>
      <imageName>mt4_pnd2_a_RGB</imageName>
      <taggedRectangles>
         <taggedRectangle height="128" width="139" x="111" y="65"/>
         <taggedRectangle height="77" width="57" x="227" y="109"/>
      </taggedRectangles>
   </image>
   <image>
      <imageName>mt4_pnd2_a_corrected_NIR</imageName>
      <taggedRectangles>
         <taggedRectangle height="128" width="139" x="111" y="65"/>
         <taggedRectangle height="77" width="57" x="227" y="109"/>
      </taggedRectangles>
   </image>
   <image>
      <imageName>mt4_pnd2_a_corrected_THERMAL</imageName>
      <taggedRectangles>
         <taggedRectangle height="128" width="139" x="111" y="65"/>
         <taggedRectangle height="77" width="57" x="227" y="109"/>
      </taggedRectangles>
   </image>
   <image>
      <imageName>mt4_pnd2_b_RGB</imageName>
      <taggedRectangles>
         <taggedRectangle height="114" width="180" x="126" y="62"/>
         <taggedRectangle height="57" width="111" x="178" y="143"/>
      </taggedRectangles>
   </image>
   <image>
      <imageName>mt4_pnd2_b_corrected_NIR</imageName>
      <taggedRectangles>
         <taggedRectangle height="114" width="180" x="126" y="62"/>
         <taggedRectangle height="57" width="111" x="178" y="143"/>
      </taggedRectangles>
   </image>
   <image>
      <imageName>mt4_pnd2_b_corrected_THERMAL</imageName>
      <taggedRectangles>
         <taggedRectangle height="114" width="180" x="126" y="62"/>
         <taggedRectangle height="57" width="111" x="178" y="143"/>
      </taggedRectangles>
   </image>
   <image>
      <imageName>mt4_pnd2_c_RGB</imageName>
      <taggedRectangles>
         <taggedRectangle height="96" width="182" x="148" y="67"/>
         <taggedRectangle height="52" width="103" x="159" y="145"/>
      </taggedRectangles>
   </image>
   <image>
      <imageName>mt4_pnd2_c_corrected_NIR</imageName>
      <taggedRectangles>
         <taggedRectangle height="96" width="182" x="148" y="67"/>
         <taggedRectangle height="52" width="103" x="159" y="145"/>
      </taggedRectangles>
   </image>
   <image>
      <imageName>mt4_pnd2_c_corrected_THERMAL</imageName>
      <taggedRectangles>
         <taggedRectangle height="96" width="182" x="148" y="67"/>
         <taggedRectangle height="52" width="103" x="159" y="145"/>
      </taggedRectangles>
   </image>
   <image>
      <imageName>mt4_pnd2_d_RGB</imageName>
      <taggedRectangles>
         <taggedRectangle height="110" width="185" x="154" y="64"/>
         <taggedRectangle height="62" width="101" x="133" y="129"/>
      </taggedRectangles>
   </image>
   <image>
      <imageName>mt4_pnd2_d_corrected_NIR</imageName>
      <taggedRectangles>
         <taggedRectangle height="110" width="185" x="154" y="64"/>
         <taggedRectangle height="62" width="101" x="133" y="129"/>
      </taggedRectangles>
   </image>
   <image>
      <imageName>mt4_pnd2_d_corrected_THERMAL</imageName>
      <taggedRectangles>
         <taggedRectangle height="110" width="185" x="154" y="64"/>
         <taggedRectangle height="62" width="101" x="133" y="129"/>
      </taggedRectangles>
   </image>
   <image>
      <imageName>mt4_pnd2_e_RGB</imageName>
      <taggedRectangles>
         <taggedRectangle height="123" width="136" x="159" y="65"/>
         <taggedRectangle height="71" width="56" x="128" y="98"/>
      </taggedRectangles>
   </image>
   <image>
      <imageName>mt4_pnd2_e_corrected_NIR</imageName>
      <taggedRectangles>
         <taggedRectangle height="123" width="136" x="159" y="65"/>
         <taggedRectangle height="71" width="56" x="128" y="98"/>
      </taggedRectangles>
   </image>
   <image>
      <imageName>mt4_pnd2_e_corrected_THERMAL</imageName>
      <taggedRectangles>
         <taggedRectangle height="123" width="136" x="159" y="65"/>
         <taggedRectangle height="71" width="56" x="128" y="98"/>
      </taggedRectangles>
   </image>
   <image>
      <imageName>mt4_pnd2_f_RGB</imageName>
      <taggedRectangles>
         <taggedRectangle height="117" width="158" x="139" y="66"/>
         <taggedRectangle height="67" width="80" x="122" y="73"/>
      </taggedRectangles>
   </image>
   <image>
      <imageName>mt4_pnd2_f_corrected_NIR</imageName>
      <taggedRectangles>
         <taggedRectangle height="117" width="158" x="139" y="66"/>
         <taggedRectangle height="67" width="80" x="122" y="73"/>
      </taggedRectangles>
   </image>
   <image>
      <imageName>mt4_pnd2_f_corrected_THERMAL</imageName>
      <taggedRectangles>
         <taggedRectangle height="117" width="158" x="139" y="66"/>
         <taggedRectangle height="67" width="80" x="122" y="73"/>
      </taggedRectangles>
   </image>
   <image>
      <imageName>mt4_pnd2_g_RGB</imageName>
      <taggedRectangles>
         <taggedRectangle height="107" width="190" x="116" y="82"/>
         <taggedRectangle height="28" width="54" x="164" y="85"/>
      </taggedRectangles>
   </image>
   <image>
      <imageName>mt4_pnd2_g_corrected_NIR</imageName>
      <taggedRectangles>
         <taggedRectangle height="107" width="190" x="116" y="82"/>
         <taggedRectangle height="28" width="54" x="164" y="85"/>
      </taggedRectangles>
   </image>
   <image>
      <imageName>mt4_pnd2_g_corrected_THERMAL</imageName>
      <taggedRectangles>
         <taggedRectangle height="107" width="190" x="116" y="82"/>
         <taggedRectangle height="28" width="54" x="164" y="85"/>
      </taggedRectangles>
   </image>
   <image>
      <imageName>mt4_pnd2_h_RGB</imageName>
      <taggedRectangles>
         <taggedRectangle height="119" width="156" x="123" y="70"/>
         <taggedRectangle height="64" width="83" x="223" y="78"/>
      </taggedRectangles>
   </image>
   <image>
      <imageName>mt4_pnd2_h_corrected_NIR</imageName>
      <taggedRectangles>
         <taggedRectangle height="119" width="156" x="123" y="70"/>
         <taggedRectangle height="64" width="83" x="223" y="78"/>
      </taggedRectangles>
   </image>
   <image>
      <imageName>mt4_pnd2_h_corrected_THERMAL</imageName>
      <taggedRectangles>
         <taggedRectangle height="119" width="156" x="123" y="70"/>
         <taggedRectangle height="64" width="83" x="223" y="78"/>
      </taggedRectangles>
   </image>
</tagset>